src/CORDIC_COS_SIN.v
module CORDIC_COS_SIN #(
    parameter DATA_WIDTH = 16,
    parameter PHASE_WIDTH = 32,
    parameter STAGE = 16
) (
    input clk,
    input rst,
    input en,
    input mode,     //0: Rotate mode, 1: Vector mode
    input signed [DATA_WIDTH-1:0] x0,
    input signed [DATA_WIDTH-1:0] y0,
    input signed [PHASE_WIDTH-1:0] phase,   //{quadrant, value}
    output valid,
    output [DATA_WIDTH:0] cos,
    output [DATA_WIDTH:0] sin
);
/*
    According to CORDIC Algorithm, let x_in = K, y_in = 0, 
    to calculate COS and SIN, x_out = cos(z_in), y_out = sin(z_in)
*/
parameter K = 32'd39797;    //K = 0.607253*2^16
//Look Up Table of arctan
parameter [PHASE_WIDTH*STAGE-1:0] atan = {32'd128, 32'd256, 32'd448, 32'd896, 32'd1856, 32'd3648, 32'd7360, 32'd14656, 32'd29312,
                                         32'd58688, 32'd117312, 32'd234368, 32'd466944, 32'd919872, 32'd1740992, 32'd2949120};

integer i, j;
wire [1:0] quadrant;
assign quadrant = phase[PHASE_WIDTH-1:PHASE_WIDTH-2];
reg signed [DATA_WIDTH:0] x_pre;
reg signed [DATA_WIDTH:0] y_pre;
reg signed [PHASE_WIDTH-1:0] z_pre;
reg signed [DATA_WIDTH:0] x [0:STAGE-1];
reg signed [DATA_WIDTH:0] y [0:STAGE-1];
reg signed [PHASE_WIDTH-1:0] z [0:STAGE-1];
reg signed [DATA_WIDTH:0] x_shift [0:STAGE-1]; 
reg signed [DATA_WIDTH:0] y_shift [0:STAGE-1];
reg [STAGE-1:0] sign;

always @(*) begin
    for(i=0; i<STAGE; i=i+1)begin
        x_shift[i] = x[i] >>> i;
        y_shift[i] = y[i] >>> i;
        sign[i] = z[i][PHASE_WIDTH-1];
    end
end

//Pre-rotation for angles which abs(phase) > pi/2
wire [DATA_WIDTH:0] x0_pos, x0_neg;
wire [DATA_WIDTH:0] y0_pos, y0_neg;
assign x0_pos = (x0 == 0) ? 0 : {1'b0, x0};
assign x0_neg = (x0 == 0) ? 0 : {1'b1, (~x0)+16'b1};
assign y0_pos = (y0 == 0) ? 0 : {1'b0, y0};
assign y0_neg = (y0 == 0) ? 0 : {1'b1, (~y0)+16'b1};
always @(posedge clk or posedge rst) begin
    if(rst)begin
        x_pre <= 0;
        y_pre <= 0;
        z_pre <= 0;
    end
    else begin
        if(en)begin
            case (quadrant)
                0:begin
                    x_pre <= x0_pos;
                    y_pre <= y0_pos;
                    z_pre <= phase;
                end
                1:begin
                    x_pre <= y0_neg;
                    y_pre <= x0_pos;
                    z_pre <= {2'b00, phase[29:0]};
                end
                2:begin
                    x_pre <= y0_pos;
                    y_pre <= x0_neg;
                    z_pre <= {2'b11, phase[29:0]};
                end
                3:begin
                    x_pre <= x0_pos;
                    y_pre <= y0_pos;
                    z_pre <= phase;
                end
            endcase
        end
        else begin
            x_pre <= 0;
            y_pre <= 0;
            z_pre <= 0;
        end
    end
end


//Iteration
always @(posedge clk or posedge rst) begin
    if(rst)begin
        for(i=0; i<STAGE; i=i+1)begin
            x[i] <= 0;
            y[i] <= 0;
            z[i] <= 0;
        end
    end
    else begin
        x[0] <= x_pre;
        y[0] <= y_pre;
        z[0] <= z_pre;
        for(i=0; i<STAGE; i=i+1)begin
            x[i+1] <= sign[i] ? x[i]+y_shift[i] : x[i]-y_shift[i];
            y[i+1] <= sign[i] ? y[i]-x_shift[i] : y[i]+x_shift[i];
            z[i+1] <= sign[i] ? z[i]+atan[32*(i+1)-1 -: 32] : z[i]-atan[32*(i+1)-1 -: 32];
        end
    end
end

assign cos = x[STAGE-1];
assign sin = y[STAGE-1];
assign valid = en_dly[STAGE];

reg [4:0] cnt;
always @(posedge clk or posedge rst) begin
    if(rst)begin
        cnt <= 0;
    end
    else begin
        if(cnt == 0)begin
            if(en)begin
                cnt <= cnt + 1;
            end
        end
        else begin
            cnt <= (cnt == 16) ? 0 : cnt+1;
        end
    end
end

reg [STAGE:0] en_dly;
always @(posedge clk or posedge rst) begin
    if(rst)begin
        en_dly <= 0;
    end
    else begin
        en_dly[0] <= en;
        for(i=0; i<STAGE; i=i+1)begin
            en_dly[i+1] <= en_dly[i];
        end
    end
end
    
endmodule

src/CORDIC_COS_SIN_tb.v
`timescale 1ns/10ps
`define CYCLE 10

module CORDIC_COS_SIN_tb ();
    
    parameter t_rst = `CYCLE*2;

    parameter DATA_WIDTH = 16;
    parameter PHASE_WIDTH = 32;
    parameter STAGE = 16;

    integer i;

    reg clk;
    reg rst;
    reg en;
    reg [DATA_WIDTH-1:0] x0;
    reg [DATA_WIDTH-1:0] y0;
    reg signed [PHASE_WIDTH-1:0] phase;
    wire valid;
    wire [DATA_WIDTH:0] cos;
    wire [DATA_WIDTH:0] sin;

    CORDIC_COS_SIN #(
        .DATA_WIDTH(DATA_WIDTH),
        .PHASE_WIDTH(PHASE_WIDTH),
        .STAGE(STAGE)
    ) cordic_cos_sin (
        .clk(clk),
        .rst(rst),
        .en(en),
        .x0(x0),
        .y0(y0),
        .phase(phase),  
        .valid(valid),
        .cos(cos),
        .sin(sin)
    );

    always #(`CYCLE/2) clk = ~clk;

    initial begin
        clk = 0; rst = 1; en = 0; phase = 0; x0 = 0; y0 = 0;
        #t_rst  rst = 0;
        #`CYCLE en = 1; x0 = 16'd39797; y0 = 0; phase = {2'd0, 30'd2949120};    //45*2^16
        #`CYCLE phase = {2'd1, 30'd2949120};
        #`CYCLE phase = {2'd2, -30'd2949120};   //-45*2^16  
        #`CYCLE phase = {2'd3, -30'd2949120};
        #`CYCLE en = 0; phase = 0;
        #5000 $finish;
    end

    initial begin
        $dumpfile("CORDIC_COS_SIN.vcd");
        $dumpvars;
        $dumpvars(0, cordic_cos_sin);
        for(i=0; i<STAGE; i=i+1)begin
            $dumpvars(1, cordic_cos_sin.x[i]);
            $dumpvars(1, cordic_cos_sin.y[i]);
            $dumpvars(1, cordic_cos_sin.z[i]);
            $dumpvars(1, cordic_cos_sin.x_shift[i]);
            $dumpvars(1, cordic_cos_sin.y_shift[i]);
        end
    end

endmodule

src/CORDIC_COS_SIN.vcd
$date
	Sat Aug 20 00:09:26 2022
$end
$version
	Icarus Verilog
$end
$timescale
	10ps
$end
$scope module CORDIC_COS_SIN_tb $end
$var wire 1 ! valid $end
$var wire 17 " sin [16:0] $end
$var wire 17 # cos [16:0] $end
$var reg 1 $ clk $end
$var reg 1 % en $end
$var reg 32 & phase [31:0] $end
$var reg 1 ' rst $end
$var reg 16 ( x0 [15:0] $end
$var reg 16 ) y0 [15:0] $end
$var integer 32 * i [31:0] $end
$scope module cordic_cos_sin $end
$var wire 1 $ clk $end
$var wire 17 + cos [16:0] $end
$var wire 1 % en $end
$var wire 1 , mode $end
$var wire 32 - phase [31:0] $end
$var wire 1 ' rst $end
$var wire 17 . sin [16:0] $end
$var wire 16 / x0 [15:0] $end
$var wire 16 0 y0 [15:0] $end
$var wire 17 1 y0_pos [16:0] $end
$var wire 17 2 y0_neg [16:0] $end
$var wire 17 3 x0_pos [16:0] $end
$var wire 17 4 x0_neg [16:0] $end
$var wire 1 ! valid $end
$var wire 2 5 quadrant [1:0] $end
$var reg 5 6 cnt [4:0] $end
$var reg 17 7 en_dly [16:0] $end
$var reg 16 8 sign [15:0] $end
$var reg 17 9 x_pre [16:0] $end
$var reg 17 : y_pre [16:0] $end
$var reg 32 ; z_pre [31:0] $end
$var integer 32 < i [31:0] $end
$upscope $end
$upscope $end
$scope module CORDIC_COS_SIN_tb $end
$scope module cordic_cos_sin $end
$upscope $end
$upscope $end
$scope module CORDIC_COS_SIN_tb $end
$scope module cordic_cos_sin $end
$var reg 17 = \x[0] [16:0] $end
$upscope $end
$upscope $end
$scope module CORDIC_COS_SIN_tb $end
$scope module cordic_cos_sin $end
$var reg 17 > \y[0] [16:0] $end
$upscope $end
$upscope $end
$scope module CORDIC_COS_SIN_tb $end
$scope module cordic_cos_sin $end
$var reg 32 ? \z[0] [31:0] $end
$upscope $end
$upscope $end
$scope module CORDIC_COS_SIN_tb $end
$scope module cordic_cos_sin $end
$var reg 17 @ \x_shift[0] [16:0] $end
$upscope $end
$upscope $end
$scope module CORDIC_COS_SIN_tb $end
$scope module cordic_cos_sin $end
$var reg 17 A \y_shift[0] [16:0] $end
$upscope $end
$upscope $end
$scope module CORDIC_COS_SIN_tb $end
$scope module cordic_cos_sin $end
$var reg 17 B \x[1] [16:0] $end
$upscope $end
$upscope $end
$scope module CORDIC_COS_SIN_tb $end
$scope module cordic_cos_sin $end
$var reg 17 C \y[1] [16:0] $end
$upscope $end
$upscope $end
$scope module CORDIC_COS_SIN_tb $end
$scope module cordic_cos_sin $end
$var reg 32 D \z[1] [31:0] $end
$upscope $end
$upscope $end
$scope module CORDIC_COS_SIN_tb $end
$scope module cordic_cos_sin $end
$var reg 17 E \x_shift[1] [16:0] $end
$upscope $end
$upscope $end
$scope module CORDIC_COS_SIN_tb $end
$scope module cordic_cos_sin $end
$var reg 17 F \y_shift[1] [16:0] $end
$upscope $end
$upscope $end
$scope module CORDIC_COS_SIN_tb $end
$scope module cordic_cos_sin $end
$var reg 17 G \x[2] [16:0] $end
$upscope $end
$upscope $end
$scope module CORDIC_COS_SIN_tb $end
$scope module cordic_cos_sin $end
$var reg 17 H \y[2] [16:0] $end
$upscope $end
$upscope $end
$scope module CORDIC_COS_SIN_tb $end
$scope module cordic_cos_sin $end
$var reg 32 I \z[2] [31:0] $end
$upscope $end
$upscope $end
$scope module CORDIC_COS_SIN_tb $end
$scope module cordic_cos_sin $end
$var reg 17 J \x_shift[2] [16:0] $end
$upscope $end
$upscope $end
$scope module CORDIC_COS_SIN_tb $end
$scope module cordic_cos_sin $end
$var reg 17 K \y_shift[2] [16:0] $end
$upscope $end
$upscope $end
$scope module CORDIC_COS_SIN_tb $end
$scope module cordic_cos_sin $end
$var reg 17 L \x[3] [16:0] $end
$upscope $end
$upscope $end
$scope module CORDIC_COS_SIN_tb $end
$scope module cordic_cos_sin $end
$var reg 17 M \y[3] [16:0] $end
$upscope $end
$upscope $end
$scope module CORDIC_COS_SIN_tb $end
$scope module cordic_cos_sin $end
$var reg 32 N \z[3] [31:0] $end
$upscope $end
$upscope $end
$scope module CORDIC_COS_SIN_tb $end
$scope module cordic_cos_sin $end
$var reg 17 O \x_shift[3] [16:0] $end
$upscope $end
$upscope $end
$scope module CORDIC_COS_SIN_tb $end
$scope module cordic_cos_sin $end
$var reg 17 P \y_shift[3] [16:0] $end
$upscope $end
$upscope $end
$scope module CORDIC_COS_SIN_tb $end
$scope module cordic_cos_sin $end
$var reg 17 Q \x[4] [16:0] $end
$upscope $end
$upscope $end
$scope module CORDIC_COS_SIN_tb $end
$scope module cordic_cos_sin $end
$var reg 17 R \y[4] [16:0] $end
$upscope $end
$upscope $end
$scope module CORDIC_COS_SIN_tb $end
$scope module cordic_cos_sin $end
$var reg 32 S \z[4] [31:0] $end
$upscope $end
$upscope $end
$scope module CORDIC_COS_SIN_tb $end
$scope module cordic_cos_sin $end
$var reg 17 T \x_shift[4] [16:0] $end
$upscope $end
$upscope $end
$scope module CORDIC_COS_SIN_tb $end
$scope module cordic_cos_sin $end
$var reg 17 U \y_shift[4] [16:0] $end
$upscope $end
$upscope $end
$scope module CORDIC_COS_SIN_tb $end
$scope module cordic_cos_sin $end
$var reg 17 V \x[5] [16:0] $end
$upscope $end
$upscope $end
$scope module CORDIC_COS_SIN_tb $end
$scope module cordic_cos_sin $end
$var reg 17 W \y[5] [16:0] $end
$upscope $end
$upscope $end
$scope module CORDIC_COS_SIN_tb $end
$scope module cordic_cos_sin $end
$var reg 32 X \z[5] [31:0] $end
$upscope $end
$upscope $end
$scope module CORDIC_COS_SIN_tb $end
$scope module cordic_cos_sin $end
$var reg 17 Y \x_shift[5] [16:0] $end
$upscope $end
$upscope $end
$scope module CORDIC_COS_SIN_tb $end
$scope module cordic_cos_sin $end
$var reg 17 Z \y_shift[5] [16:0] $end
$upscope $end
$upscope $end
$scope module CORDIC_COS_SIN_tb $end
$scope module cordic_cos_sin $end
$var reg 17 [ \x[6] [16:0] $end
$upscope $end
$upscope $end
$scope module CORDIC_COS_SIN_tb $end
$scope module cordic_cos_sin $end
$var reg 17 \ \y[6] [16:0] $end
$upscope $end
$upscope $end
$scope module CORDIC_COS_SIN_tb $end
$scope module cordic_cos_sin $end
$var reg 32 ] \z[6] [31:0] $end
$upscope $end
$upscope $end
$scope module CORDIC_COS_SIN_tb $end
$scope module cordic_cos_sin $end
$var reg 17 ^ \x_shift[6] [16:0] $end
$upscope $end
$upscope $end
$scope module CORDIC_COS_SIN_tb $end
$scope module cordic_cos_sin $end
$var reg 17 _ \y_shift[6] [16:0] $end
$upscope $end
$upscope $end
$scope module CORDIC_COS_SIN_tb $end
$scope module cordic_cos_sin $end
$var reg 17 ` \x[7] [16:0] $end
$upscope $end
$upscope $end
$scope module CORDIC_COS_SIN_tb $end
$scope module cordic_cos_sin $end
$var reg 17 a \y[7] [16:0] $end
$upscope $end
$upscope $end
$scope module CORDIC_COS_SIN_tb $end
$scope module cordic_cos_sin $end
$var reg 32 b \z[7] [31:0] $end
$upscope $end
$upscope $end
$scope module CORDIC_COS_SIN_tb $end
$scope module cordic_cos_sin $end
$var reg 17 c \x_shift[7] [16:0] $end
$upscope $end
$upscope $end
$scope module CORDIC_COS_SIN_tb $end
$scope module cordic_cos_sin $end
$var reg 17 d \y_shift[7] [16:0] $end
$upscope $end
$upscope $end
$scope module CORDIC_COS_SIN_tb $end
$scope module cordic_cos_sin $end
$var reg 17 e \x[8] [16:0] $end
$upscope $end
$upscope $end
$scope module CORDIC_COS_SIN_tb $end
$scope module cordic_cos_sin $end
$var reg 17 f \y[8] [16:0] $end
$upscope $end
$upscope $end
$scope module CORDIC_COS_SIN_tb $end
$scope module cordic_cos_sin $end
$var reg 32 g \z[8] [31:0] $end
$upscope $end
$upscope $end
$scope module CORDIC_COS_SIN_tb $end
$scope module cordic_cos_sin $end
$var reg 17 h \x_shift[8] [16:0] $end
$upscope $end
$upscope $end
$scope module CORDIC_COS_SIN_tb $end
$scope module cordic_cos_sin $end
$var reg 17 i \y_shift[8] [16:0] $end
$upscope $end
$upscope $end
$scope module CORDIC_COS_SIN_tb $end
$scope module cordic_cos_sin $end
$var reg 17 j \x[9] [16:0] $end
$upscope $end
$upscope $end
$scope module CORDIC_COS_SIN_tb $end
$scope module cordic_cos_sin $end
$var reg 17 k \y[9] [16:0] $end
$upscope $end
$upscope $end
$scope module CORDIC_COS_SIN_tb $end
$scope module cordic_cos_sin $end
$var reg 32 l \z[9] [31:0] $end
$upscope $end
$upscope $end
$scope module CORDIC_COS_SIN_tb $end
$scope module cordic_cos_sin $end
$var reg 17 m \x_shift[9] [16:0] $end
$upscope $end
$upscope $end
$scope module CORDIC_COS_SIN_tb $end
$scope module cordic_cos_sin $end
$var reg 17 n \y_shift[9] [16:0] $end
$upscope $end
$upscope $end
$scope module CORDIC_COS_SIN_tb $end
$scope module cordic_cos_sin $end
$var reg 17 o \x[10] [16:0] $end
$upscope $end
$upscope $end
$scope module CORDIC_COS_SIN_tb $end
$scope module cordic_cos_sin $end
$var reg 17 p \y[10] [16:0] $end
$upscope $end
$upscope $end
$scope module CORDIC_COS_SIN_tb $end
$scope module cordic_cos_sin $end
$var reg 32 q \z[10] [31:0] $end
$upscope $end
$upscope $end
$scope module CORDIC_COS_SIN_tb $end
$scope module cordic_cos_sin $end
$var reg 17 r \x_shift[10] [16:0] $end
$upscope $end
$upscope $end
$scope module CORDIC_COS_SIN_tb $end
$scope module cordic_cos_sin $end
$var reg 17 s \y_shift[10] [16:0] $end
$upscope $end
$upscope $end
$scope module CORDIC_COS_SIN_tb $end
$scope module cordic_cos_sin $end
$var reg 17 t \x[11] [16:0] $end
$upscope $end
$upscope $end
$scope module CORDIC_COS_SIN_tb $end
$scope module cordic_cos_sin $end
$var reg 17 u \y[11] [16:0] $end
$upscope $end
$upscope $end
$scope module CORDIC_COS_SIN_tb $end
$scope module cordic_cos_sin $end
$var reg 32 v \z[11] [31:0] $end
$upscope $end
$upscope $end
$scope module CORDIC_COS_SIN_tb $end
$scope module cordic_cos_sin $end
$var reg 17 w \x_shift[11] [16:0] $end
$upscope $end
$upscope $end
$scope module CORDIC_COS_SIN_tb $end
$scope module cordic_cos_sin $end
$var reg 17 x \y_shift[11] [16:0] $end
$upscope $end
$upscope $end
$scope module CORDIC_COS_SIN_tb $end
$scope module cordic_cos_sin $end
$var reg 17 y \x[12] [16:0] $end
$upscope $end
$upscope $end
$scope module CORDIC_COS_SIN_tb $end
$scope module cordic_cos_sin $end
$var reg 17 z \y[12] [16:0] $end
$upscope $end
$upscope $end
$scope module CORDIC_COS_SIN_tb $end
$scope module cordic_cos_sin $end
$var reg 32 { \z[12] [31:0] $end
$upscope $end
$upscope $end
$scope module CORDIC_COS_SIN_tb $end
$scope module cordic_cos_sin $end
$var reg 17 | \x_shift[12] [16:0] $end
$upscope $end
$upscope $end
$scope module CORDIC_COS_SIN_tb $end
$scope module cordic_cos_sin $end
$var reg 17 } \y_shift[12] [16:0] $end
$upscope $end
$upscope $end
$scope module CORDIC_COS_SIN_tb $end
$scope module cordic_cos_sin $end
$var reg 17 ~ \x[13] [16:0] $end
$upscope $end
$upscope $end
$scope module CORDIC_COS_SIN_tb $end
$scope module cordic_cos_sin $end
$var reg 17 !" \y[13] [16:0] $end
$upscope $end
$upscope $end
$scope module CORDIC_COS_SIN_tb $end
$scope module cordic_cos_sin $end
$var reg 32 "" \z[13] [31:0] $end
$upscope $end
$upscope $end
$scope module CORDIC_COS_SIN_tb $end
$scope module cordic_cos_sin $end
$var reg 17 #" \x_shift[13] [16:0] $end
$upscope $end
$upscope $end
$scope module CORDIC_COS_SIN_tb $end
$scope module cordic_cos_sin $end
$var reg 17 $" \y_shift[13] [16:0] $end
$upscope $end
$upscope $end
$scope module CORDIC_COS_SIN_tb $end
$scope module cordic_cos_sin $end
$var reg 17 %" \x[14] [16:0] $end
$upscope $end
$upscope $end
$scope module CORDIC_COS_SIN_tb $end
$scope module cordic_cos_sin $end
$var reg 17 &" \y[14] [16:0] $end
$upscope $end
$upscope $end
$scope module CORDIC_COS_SIN_tb $end
$scope module cordic_cos_sin $end
$var reg 32 '" \z[14] [31:0] $end
$upscope $end
$upscope $end
$scope module CORDIC_COS_SIN_tb $end
$scope module cordic_cos_sin $end
$var reg 17 (" \x_shift[14] [16:0] $end
$upscope $end
$upscope $end
$scope module CORDIC_COS_SIN_tb $end
$scope module cordic_cos_sin $end
$var reg 17 )" \y_shift[14] [16:0] $end
$upscope $end
$upscope $end
$scope module CORDIC_COS_SIN_tb $end
$scope module cordic_cos_sin $end
$var reg 17 *" \x[15] [16:0] $end
$upscope $end
$upscope $end
$scope module CORDIC_COS_SIN_tb $end
$scope module cordic_cos_sin $end
$var reg 17 +" \y[15] [16:0] $end
$upscope $end
$upscope $end
$scope module CORDIC_COS_SIN_tb $end
$scope module cordic_cos_sin $end
$var reg 32 ," \z[15] [31:0] $end
$upscope $end
$upscope $end
$scope module CORDIC_COS_SIN_tb $end
$scope module cordic_cos_sin $end
$var reg 17 -" \x_shift[15] [16:0] $end
$upscope $end
$upscope $end
$scope module CORDIC_COS_SIN_tb $end
$scope module cordic_cos_sin $end
$var reg 17 ." \y_shift[15] [16:0] $end
$upscope $end
$upscope $end
$enddefinitions $end
#0
$dumpvars
b0 ."
b0 -"
b0 ,"
b0 +"
b0 *"
b0 )"
b0 ("
b0 '"
b0 &"
b0 %"
b0 $"
b0 #"
b0 ""
b0 !"
b0 ~
b0 }
b0 |
b0 {
b0 z
b0 y
b0 x
b0 w
b0 v
b0 u
b0 t
b0 s
b0 r
b0 q
b0 p
b0 o
b0 n
b0 m
b0 l
b0 k
b0 j
b0 i
b0 h
b0 g
b0 f
b0 e
b0 d
b0 c
b0 b
b0 a
b0 `
b0 _
b0 ^
b0 ]
b0 \
b0 [
b0 Z
b0 Y
b0 X
b0 W
b0 V
b0 U
b0 T
b0 S
b0 R
b0 Q
b0 P
b0 O
b0 N
b0 M
b0 L
b0 K
b0 J
b0 I
b0 H
b0 G
b0 F
b0 E
b0 D
b0 C
b0 B
b0 A
b0 @
b0 ?
b0 >
b0 =
b10000 <
b0 ;
b0 :
b0 9
b0 8
b0 7
b0 6
b0 5
b0 4
b0 3
b0 2
b0 1
b0 0
b0 /
b0 .
b0 -
z,
b0 +
b10000 *
b0 )
b0 (
1'
b0 &
0%
0$
b0 #
b0 "
0!
$end
#500
b0 ,"
b0 +"
b0 *"
b0 '"
b0 &"
b0 %"
b0 ""
b0 !"
b0 ~
b0 {
b0 z
b0 y
b0 v
b0 u
b0 t
b0 q
b0 p
b0 o
b0 l
b0 k
b0 j
b0 g
b0 f
b0 e
b0 b
b0 a
b0 `
b0 ]
b0 \
b0 [
b0 X
b0 W
b0 V
b0 S
b0 R
b0 Q
b0 N
b0 M
b0 L
b0 I
b0 H
b0 G
b0 D
b0 C
b0 B
b0 ?
b0 >
b0 =
b10000 <
1$
#1000
0$
#1500
b0 ,"
b0 +"
b0 *"
b0 '"
b0 &"
b0 %"
b0 ""
b0 !"
b0 ~
b0 {
b0 z
b0 y
b0 v
b0 u
b0 t
b0 q
b0 p
b0 o
b0 l
b0 k
b0 j
b0 g
b0 f
b0 e
b0 b
b0 a
b0 `
b0 ]
b0 \
b0 [
b0 X
b0 W
b0 V
b0 S
b0 R
b0 Q
b0 N
b0 M
b0 L
b0 I
b0 H
b0 G
b0 D
b0 C
b0 B
b0 ?
b0 >
b0 =
b10000 <
1$
#2000
0$
0'
#2500
b0 ."
b0 -"
b0 )"
b0 ("
b0 $"
b0 #"
b0 }
b0 |
b0 x
b0 w
b0 s
b0 r
b0 n
b0 m
b0 i
b0 h
b0 d
b0 c
b0 _
b0 ^
b0 Z
b0 Y
b0 U
b0 T
b0 P
b0 O
b0 K
b0 J
b1111111111111110 8
b0 F
b0 E
b0 A
b0 @
b11111111111111111111111100000000 ,"
b0 +"
b0 *"
b11111111111111111111111001000000 '"
b0 &"
b0 %"
b11111111111111111111110010000000 ""
b0 !"
b0 ~
b11111111111111111111100011000000 {
b0 z
b0 y
b11111111111111111111000111000000 v
b0 u
b0 t
b11111111111111111110001101000000 q
b0 p
b0 o
b11111111111111111100011011000000 l
b0 k
b0 j
b11111111111111111000110110000000 g
b0 f
b0 e
b11111111111111110001101011000000 b
b0 a
b0 `
b11111111111111100011010111000000 ]
b0 \
b0 [
b11111111111111000110110010000000 X
b0 W
b0 V
b11111111111110001110000000000000 S
b0 R
b0 Q
b11111111111100011111011011000000 N
b0 M
b0 L
b11111111111001010110111101000000 I
b0 H
b0 G
b11111111110100110000000000000000 D
b0 C
b0 B
b0 ?
b0 >
b0 =
b10000 <
1$
#3000
b1001101101110101 3
b10110010010001011 4
0$
b1011010000000000000000 &
b1011010000000000000000 -
b1001101101110101 (
b1001101101110101 /
1%
#3500
b0 ."
b0 -"
b0 )"
b0 ("
b0 $"
b0 #"
b0 }
b0 |
b0 x
b0 w
b0 s
b0 r
b0 n
b0 m
b0 i
b0 h
b0 d
b0 c
b0 _
b0 ^
b0 Z
b0 Y
b0 U
b0 T
b0 P
b0 O
b0 K
b0 J
b0 F
b0 E
b0 A
b0 @
b1011010000000000000000 ;
b1001101101110101 9
b11111111111111111111111101000000 ,"
b0 +"
b0 *"
b11111111111111111111111001000000 '"
b0 &"
b0 %"
b11111111111111111111110001000000 ""
b0 !"
b0 ~
b11111111111111111111100100000000 {
b0 z
b0 y
b11111111111111111111000110000000 v
b0 u
b0 t
b11111111111111111110001110000000 q
b0 p
b0 o
b11111111111111111100011011000000 l
b0 k
b0 j
b11111111111111111000110101000000 g
b0 f
b0 e
b11111111111111110001101100000000 b
b0 a
b0 `
b11111111111111100011011011000000 ]
b0 \
b0 [
b11111111111111000111001110000000 X
b0 W
b0 V
b11111111111110010001011011000000 S
b0 R
b0 Q
b11111111111100110111100010000000 N
b0 M
b0 L
b11111111111011011001000011000000 I
b0 H
b0 G
b11111111110100110000000000000000 D
b0 C
b0 B
b0 ?
b0 >
b0 =
b1 6
b1 7
b10000 <
1$
#4000
b1 5
0$
b1000000001011010000000000000000 &
b1000000001011010000000000000000 -
#4500
b0 ."
b0 -"
b0 )"
b0 ("
b0 $"
b0 #"
b0 }
b0 |
b0 x
b0 w
b0 s
b0 r
b0 n
b0 m
b0 i
b0 h
b0 d
b0 c
b0 _
b0 ^
b0 Z
b0 Y
b0 U
b0 T
b0 P
b0 O
b0 K
b0 J
b0 F
b0 E
b0 A
b1001101101110101 @
b11 7
b10 6
b11111111111111111111111101000000 ,"
b0 +"
b0 *"
b11111111111111111111111000000000 '"
b0 &"
b0 %"
b11111111111111111111110010000000 ""
b0 !"
b0 ~
b11111111111111111111100011000000 {
b0 z
b0 y
b11111111111111111111000111000000 v
b0 u
b0 t
b11111111111111111110001110000000 q
b0 p
b0 o
b11111111111111111100011010000000 l
b0 k
b0 j
b11111111111111111000110110000000 g
b0 f
b0 e
b11111111111111110001110000000000 b
b0 a
b0 `
b11111111111111100011110111000000 ]
b0 \
b0 [
b11111111111111001010101001000000 X
b0 W
b0 V
b11111111111110101001100010000000 S
b0 R
b0 Q
b11111111111110111001101000000000 N
b0 M
b0 L
b11111111111011011001000011000000 I
b0 H
b0 G
b11111111110100110000000000000000 D
b0 C
b0 B
b1011010000000000000000 ?
b0 >
b1001101101110101 =
b1001101101110101 :
b0 9
b10000 <
1$
#5000
b10 5
0$
b10111111110100110000000000000000 &
b10111111110100110000000000000000 -
#5500
b0 ."
b0 -"
b0 )"
b0 ("
b0 $"
b0 #"
b0 }
b0 |
b0 x
b0 w
b0 s
b0 r
b0 n
b0 m
b0 i
b0 h
b0 d
b0 c
b0 _
b0 ^
b0 Z
b0 Y
b0 U
b0 T
b0 P
b0 O
b0 K
b0 J
b1111111111101100 8
b100110110111010 F
b100110110111010 E
b1001101101110101 A
b0 @
b11111111110100110000000000000000 ;
b10110010010001011 :
b11111111111111111111111100000000 ,"
b0 +"
b0 *"
b11111111111111111111111001000000 '"
b0 &"
b0 %"
b11111111111111111111110001000000 ""
b0 !"
b0 ~
b11111111111111111111100100000000 {
b0 z
b0 y
b11111111111111111111000111000000 v
b0 u
b0 t
b11111111111111111110001101000000 q
b0 p
b0 o
b11111111111111111100011011000000 l
b0 k
b0 j
b11111111111111111000111010000000 g
b0 f
b0 e
b11111111111111110010001100000000 b
b0 a
b0 `
b11111111111111100111010010000000 ]
b0 \
b0 [
b11111111111111100010110000000000 X
b0 W
b0 V
b101011101000000000 S
b0 R
b0 Q
b11111111111110111001101000000000 N
b0 M
b0 L
b11111111111011011001000011000000 I
b0 H
b0 G
b0 D
b1001101101110101 C
b1001101101110101 B
b1011010000000000000000 ?
b1001101101110101 >
b0 =
b11 6
b111 7
b10000 <
1$
#6000
b11 5
0$
b11111111110100110000000000000000 &
b11111111110100110000000000000000 -
#6500
b0 ."
b0 -"
b0 )"
b0 ("
b0 $"
b0 #"
b0 }
b0 |
b0 x
b0 w
b0 s
b0 r
b0 n
b0 m
b0 i
b0 h
b0 d
b0 c
b0 _
b0 ^
b0 Z
b0 Y
b0 U
b0 T
b0 P
b0 O
b11101001001011 K
b1001101101110 J
b100110110111010 F
b11011001001000101 E
b1111111111101101 8
b10110010010001011 A
b0 @
b1111 7
b100 6
b11111111111111111111111101000000 ,"
b0 +"
b0 *"
b11111111111111111111111000000000 '"
b0 &"
b0 %"
b11111111111111111111110010000000 ""
b0 !"
b0 ~
b11111111111111111111100100000000 {
b0 z
b0 y
b11111111111111111111000110000000 v
b0 u
b0 t
b11111111111111111110001110000000 q
b0 p
b0 o
b11111111111111111100011111000000 l
b0 k
b0 j
b11111111111111111001010110000000 g
b0 f
b0 e
b11111111111111110101100111000000 b
b0 a
b0 `
b11111111111111111111011001000000 ]
b0 \
b0 [
b11111111111111110010011010000000 X
b0 W
b0 V
b101011101000000000 S
b0 R
b0 Q
b11111111111110111001101000000000 N
b0 M
b0 L
b11111111111001010110111101000000 I
b1110100100101111 H
b100110110111011 G
b0 D
b1001101101110101 C
b10110010010001011 B
b11111111110100110000000000000000 ?
b10110010010001011 >
b0 =
b0 :
b1001101101110101 9
b10000 <
1$
#7000
b0 5
0$
b0 &
b0 -
0%
#7500
b0 ."
b0 -"
b0 )"
b0 ("
b0 $"
b0 #"
b0 }
b0 |
b0 x
b0 w
b0 s
b0 r
b0 n
b0 m
b0 i
b0 h
b0 d
b0 c
b1111111100101101 8
b0 _
b0 ^
b0 Z
b0 Y
b0 U
b0 T
b1101010111000 P
b1000100000000 O
b1001101101110 K
b11100010110110100 J
b11011001001000101 F
b11011001001000101 E
b0 A
b1001101101110101 @
b0 ;
b0 9
b11111111111111111111111100000000 ,"
b0 +"
b0 *"
b11111111111111111111111001000000 '"
b0 &"
b0 %"
b11111111111111111111110010000000 ""
b0 !"
b0 ~
b11111111111111111111100011000000 {
b0 z
b0 y
b11111111111111111111000111000000 v
b0 u
b0 t
b11111111111111111110010010000000 q
b0 p
b0 o
b11111111111111111100111011000000 l
b0 k
b0 j
b11111111111111111100110001000000 g
b0 f
b0 e
b1101101110000000 b
b0 a
b0 `
b1111000011000000 ]
b0 \
b0 [
b11111111111111110010011010000000 X
b0 W
b0 V
b101011101000000000 S
b0 R
b0 Q
b11111111111100110111100010000000 N
b1101010111000001 M
b1000100000000110 L
b11111111111001010110111101000000 I
b100110110111010 H
b10001011011010001 G
b0 D
b10110010010001011 C
b10110010010001011 B
b11111111110100110000000000000000 ?
b0 >
b1001101101110101 =
b101 6
b11110 7
b10000 <
1$
#8000
0$
